Linkedin_saved_posts_search/__init__.py
Linkedin_saved_posts_search/main.py
Linkedin_saved_posts_search-0.3.0.dist-info/METADATA
Linkedin_saved_posts_search-0.3.0.dist-info/WHEEL
Linkedin_saved_posts_search-0.3.0.dist-info/entry_points.txt
Linkedin_saved_posts_search-0.3.0.dist-info/top_level.txt
Linkedin_saved_posts_search-0.3.0.dist-info/RECORD
